tool_utils/__init__.py
tool_utils/print_test.py
tool_utils-0.0.4.dist-info/METADATA
tool_utils-0.0.4.dist-info/RECORD
tool_utils-0.0.4.dist-info/WHEEL
tool_utils-0.0.4.dist-info/top_level.txt
